seal5/__init__.py
seal5/build_cache.py
seal5/dependencies.py
seal5/flow.py
seal5/index.py
seal5/logging.py
seal5/metrics.py
seal5/model.py
seal5/model_utils.py
seal5/pass_list.py
seal5/passes.py
seal5/riscv_utils.py
seal5/settings.py
seal5/testgen_utils.py
seal5/types.py
seal5/utils.py
seal5/version.py
seal5/wrapper.py
seal5/backends/__init__.py
seal5/backends/coredsl2/__init__.py
seal5/backends/coredsl2/visitor.py
seal5/backends/coredsl2/writer.py
seal5/backends/llvmir/__init__.py
seal5/backends/llvmir/writer.py
seal5/backends/patterngen/__init__.py
seal5/backends/patterngen/writer.py
seal5/backends/report/__init__.py
seal5/backends/report/diff/__init__.py
seal5/backends/report/diff/writer.py
seal5/backends/report/pattern_gen/__init__.py
seal5/backends/report/pattern_gen/writer.py
seal5/backends/report/properties/__init__.py
seal5/backends/report/properties/writer.py
seal5/backends/report/status/__init__.py
seal5/backends/report/status/writer.py
seal5/backends/report/test_results/__init__.py
seal5/backends/report/test_results/writer.py
seal5/backends/report/times/__init__.py
seal5/backends/report/times/writer.py
seal5/backends/riscv_features/__init__.py
seal5/backends/riscv_features/writer.py
seal5/backends/riscv_features/templates/__init__.py
seal5/backends/riscv_features/templates/riscv_features.mako
seal5/backends/riscv_features/templates/riscv_features_experimental_new.mako
seal5/backends/riscv_features/templates/riscv_features_experimental_new_slim.mako
seal5/backends/riscv_features/templates/riscv_features_new.mako
seal5/backends/riscv_features/templates/riscv_features_new_slim.mako
seal5/backends/riscv_features/templates/test_riscv_attributes.mako
seal5/backends/riscv_field_types/__init__.py
seal5/backends/riscv_field_types/writer.py
seal5/backends/riscv_gisel_legalizer/__init__.py
seal5/backends/riscv_gisel_legalizer/writer.py
seal5/backends/riscv_instr_info/__init__.py
seal5/backends/riscv_instr_info/writer.py
seal5-0.3.3.dist-info/licenses/LICENSE
seal5-0.3.3.dist-info/METADATA
seal5-0.3.3.dist-info/WHEEL
seal5-0.3.3.dist-info/entry_points.txt
seal5-0.3.3.dist-info/top_level.txt
seal5-0.3.3.dist-info/RECORD
