Metadata-Version: 2.4
Name: seal5
Version: 0.3.3
Summary: Seal5 - Semi-automated LLVM Support for RISC-V Extensions including Autovectorization
Author-email: Philipp van Kempen <philipp.van-kempen@tum.de>
Maintainer-email: Philipp van Kempen <philipp.van-kempen@tum.de>
License: Apache-2.0
Project-URL: Homepage, https://tum-ei-eda.github.io/seal5
Project-URL: Documentation, https://tum-ei-eda.github.io/seal5
Project-URL: Repository, https://github.com/tum-ei-eda/seal5.git
Project-URL: Bug Tracker, https://github.com/tum-ei-eda/seal5/issues
Requires-Python: >=3.10
License-File: LICENSE
Requires-Dist: gitpython
Requires-Dist: pyyaml
Requires-Dist: m2isar==0.0.6
Requires-Dist: importlib_resources
Requires-Dist: dacite
Requires-Dist: mako
Requires-Dist: tqdm
Requires-Dist: pandas
Requires-Dist: tabulate
Requires-Dist: psutil
Dynamic: license-file
